AUTHORS
LICENSE
MANIFEST.in
README.rst
VERSION
pygcat.py
setup.py
pygcat.egg-info/PKG-INFO
pygcat.egg-info/SOURCES.txt
pygcat.egg-info/dependency_links.txt
pygcat.egg-info/not-zip-safe
pygcat.egg-info/pbr.json
pygcat.egg-info/requires.txt
pygcat.egg-info/top_level.txt