Metadata-Version: 1.1
Name: pygcat
Version: 0.6.1
Summary: Extract statistical information from PostgreSQL.
Home-page: https://pygcat.readthedocs.org/
Author: Rodolphe Quiédeville
Author-email: rodolphe@quiedeville.org
License: BSD
Download-URL: https://gitlab.com/rodo/pygcat/
Keywords: database postgresql statistics pg_stat_statement
Platform: UNKNOWN
Classifier: Programming Language :: Python :: 2.7
Classifier: Development Status :: 3 - Alpha
Classifier: License :: OSI Approved :: BSD License
